pyfunc2/__init__.py
pyfunc2/_version.py
pyfunc2/all_lasts.py
pyfunc2/email_update.py
pyfunc2/img_to_base64.py
pyfunc2/lasts.py
pyfunc2/to_lower_case.py
pyfunc2/config/__init__.py
pyfunc2/config/ftp_download.py
pyfunc2/config/ftp_update.py
pyfunc2/config/get_config.py
pyfunc2/config/get_email_path.py
pyfunc2/config/get_ftp_path.py
pyfunc2/csv/__init__.py
pyfunc2/csv/load_csv_pandas.py
pyfunc2/csv/load_csv_with_comma_quotas.py
pyfunc2/email/__init__.py
pyfunc2/email/all_lasts.py
pyfunc2/email/connect.py
pyfunc2/email/delete_emails.py
pyfunc2/email/download_all_attachments_in_inbox.py
pyfunc2/email/download_attachments.py
pyfunc2/email/download_attachments_in_email.py
pyfunc2/email/download_emails.py
pyfunc2/email/email_update.py
pyfunc2/email/get_path_file.py
pyfunc2/email/lasts.py
pyfunc2/file/__init__.py
pyfunc2/file/append.py
pyfunc2/file/archive_path_list.py
pyfunc2/file/check_and_create_path.py
pyfunc2/file/check_and_create_path_from_filepath.py
pyfunc2/file/check_existing_folder_list_in_path.py
pyfunc2/file/convert_pdf_to_base64.py
pyfunc2/file/create.py
pyfunc2/file/dir_list.py
pyfunc2/file/file_list.py
pyfunc2/file/find_duplicates.py
pyfunc2/file/get_filename_from_path.py
pyfunc2/file/get_hash.py
pyfunc2/file/get_hash_sha256.py
pyfunc2/file/is_file_hidden.py
pyfunc2/file/is_path_hidden.py
pyfunc2/file/move_duplicate_files.py
pyfunc2/file/move_file.py
pyfunc2/file/pdf_merge.py
pyfunc2/file/read_as_array.py
pyfunc2/file/read_as_text.py
pyfunc2/file/remove_duplicates.py
pyfunc2/file/remove_duplicates_in_path.py
pyfunc2/file/remove_empty_folders.py
pyfunc2/file/sum_year_from_path_to_file.py
pyfunc2/file/update.py
pyfunc2/function/__init__.py
pyfunc2/function/arrayElementsAreIncluded.py
pyfunc2/function/differenceElementsInArrays.py
pyfunc2/function/extract_domain_name_from_url.py
pyfunc2/function/flat_array.py
pyfunc2/function/get_domain_from_url.py
pyfunc2/function/get_subdomain_from_url.py
pyfunc2/github/__init__.py
pyfunc2/github/change_default_branch.py
pyfunc2-0.1.55.dist-info/METADATA
pyfunc2-0.1.55.dist-info/WHEEL
pyfunc2-0.1.55.dist-info/top_level.txt
pyfunc2-0.1.55.dist-info/RECORD
