Metadata-Version: 2.4
Name: pyfunc2
Version: 0.1.55
Summary: libs for cameramonit, ocr, fin-officer, cfo, and other projects
Home-page: https://www.pyfunc.com
Author: Tom Sapletta
Author-email: tom@sapletta.com
Maintainer: pyfunc developers
Maintainer-email: info@softreck.dev
License: Apache-2.0
Project-URL: Repository, https://github.com/pyfunc/lib
Project-URL: Changelog, https://github.com/pyfunc/lib/releases
Project-URL: Wiki, https://github.com/pyfunc/lib/wiki
Project-URL: Issue Tracker, https://github.com/pyfunc/lib/issues/new
Keywords: python,pyfunc,pyfunc2,pyfunc3,pyfunc
Classifier: License :: OSI Approved :: Apache Software License
Classifier: Programming Language :: Python
Classifier: Programming Language :: Python :: 3
Classifier: Programming Language :: Python :: 3.7
Classifier: Programming Language :: Python :: 3.8
Classifier: Programming Language :: Python :: 3.9
Classifier: Programming Language :: Python :: 3.10
Classifier: Programming Language :: Python :: 3.11
Requires-Python: >=3.7
Requires-Dist: pandas
Dynamic: author
Dynamic: author-email
Dynamic: classifier
Dynamic: description
Dynamic: description-content-type
Dynamic: home-page
Dynamic: keywords
Dynamic: license
Dynamic: maintainer
Dynamic: maintainer-email
Dynamic: project-url
Dynamic: requires-dist
Dynamic: requires-python
Dynamic: summary
